{
    "parent": "minecraft:recipes/root",
    "rewards": {
        "recipes": [
            "consistency_plus:mossy_andesite_bricks_crafting",
            "consistency_plus:andesite_bricks_mossify"
        ],
        "criteria": {
            "has_MossyBlock": {
                "trigger": "minecraft:inventory_changed",
                "conditions": {
                    "items": [
                        {
                            "item": "minecraft:andesite"
                        }
                    ]
                }
            }
        }
    }
}