{
  "blue_ice_slab": {
    "type": "slab"
  },
  "blue_ice_stairs": {
    "type": "stairs"
  },
  "blue_ice_wall": {
    "type": "wall"
  },
  "blue_ice_gate": {
    "type": "gate"
  },
  "polished_blue_ice": {},
  "polished_blue_ice_slab": {
    "type": "slab"
  },
  "polished_blue_ice_stairs": {
    "type": "stairs"
  },
  "polished_blue_ice_wall": {
    "type": "wall"
  },
  "polished_blue_ice_gate": {
    "type": "gate"
  },
  "smooth_blue_ice": {},
  "smooth_blue_ice_slab": {
    "type": "slab"
  },
  "smooth_blue_ice_stairs": {
    "type": "stairs"
  },
  "smooth_blue_ice_wall": {
    "type": "wall"
  },
  "smooth_blue_ice_gate": {
    "type": "gate"
  },
  "blue_ice_bricks": {},
  "blue_ice_brick_slab": {
    "type": "slab"
  },
  "blue_ice_brick_stairs": {
    "type": "stairs"
  },
  "blue_ice_brick_wall": {
    "type": "wall"
  },
  "blue_ice_brick_gate": {
    "type": "gate"
  },
  "cut_blue_ice": {},
  "cut_blue_ice_slab": {
    "type": "slab"
  },
  "cut_blue_ice_stairs": {
    "type": "stairs"
  },
  "cut_blue_ice_wall": {
    "type": "wall"
  },
  "cut_blue_ice_gate": {
    "type": "gate"
  },
  "blue_ice_tiles": {},
  "blue_ice_tile_slab": {
    "type": "slab"
  },
  "blue_ice_tile_stairs": {
    "type": "stairs"
  },
  "blue_ice_tile_wall": {
    "type": "wall"
  },
  "blue_ice_tile_gate": {
    "type": "gate"
  },
  "chiseled_blue_ice": {
  },
  "carved_blue_ice": {
  },
  "blue_ice_pillar": {
    "type": "pillar"
  },
  "blue_ice_corner_pillar": {
  }
}